kerana/Kerana.py
kerana/__init__.py
kerana/_version.py
kerana/completer.py
kerana-0.0.2a0.data/scripts/kerana
kerana-0.0.2a0.data/scripts/kerana_completer
kerana-0.0.2a0.dist-info/licenses/LICENSE
kerana-0.0.2a0.dist-info/METADATA
kerana-0.0.2a0.dist-info/WHEEL
kerana-0.0.2a0.dist-info/top_level.txt
kerana-0.0.2a0.dist-info/RECORD
