Metadata-Version: 2.4
Name: Kerana
Version: 0.0.2a0
Summary: MongoDB and ElasticSearch tools
Home-page: https://github.com/colav/Kerana
Author: Colav
Author-email: colav@udea.edu.co
License: BSD
License-File: LICENSE
Requires-Dist: pymongo
Requires-Dist: elasticsearch
Requires-Dist: elasticsearch_dsl
Requires-Dist: progress
Dynamic: author
Dynamic: author-email
Dynamic: description
Dynamic: description-content-type
Dynamic: home-page
Dynamic: license
Dynamic: license-file
Dynamic: requires-dist
Dynamic: summary
